animate_svg/__init__.py
animate_svg/gen_defs.py
animate_svg/py.typed
animate_svg-0.1.0.dist-info/METADATA
animate_svg-0.1.0.dist-info/WHEEL
animate_svg-0.1.0.dist-info/RECORD
