Metadata-Version: 2.4
Name: animate-svg
Version: 0.1.0
Summary: Add your description here
Author-email: Maxwell Ludden <max@ludden.dev>
Requires-Python: >=3.13
Requires-Dist: openai>=1.95.1
Requires-Dist: rich-color-ext>=0.1.4
Requires-Dist: rich-gradient>=0.3.6
Requires-Dist: rich>=14.1.0
